bugbane/__init__.py
bugbane/__main__.py
bugbane/modules/__init__.py
bugbane/modules/build_type.py
bugbane/modules/builds.py
bugbane/modules/corpus_utils.py
bugbane/modules/factory.py
bugbane/modules/file_utils.py
bugbane/modules/format.py
bugbane/modules/fuzz_data_suite.py
bugbane/modules/log.py
bugbane/modules/process.py
bugbane/modules/string_utils.py
bugbane/modules/fuzzer_cmd/__init__.py
bugbane/modules/fuzzer_cmd/aflplusplus.py
bugbane/modules/fuzzer_cmd/factory.py
bugbane/modules/fuzzer_cmd/fuzzer_cmd.py
bugbane/modules/fuzzer_cmd/gofuzz.py
bugbane/modules/fuzzer_cmd/libfuzzer.py
bugbane/modules/fuzzer_info/__init__.py
bugbane/modules/fuzzer_info/aflplusplus.py
bugbane/modules/fuzzer_info/factory.py
bugbane/modules/fuzzer_info/fuzzer_info.py
bugbane/modules/fuzzer_info/gofuzz.py
bugbane/modules/fuzzer_info/libfuzzer.py
bugbane/modules/stats/__init__.py
bugbane/modules/stats/factory.py
bugbane/modules/stats/stats.py
bugbane/modules/stats/coverage/__init__.py
bugbane/modules/stats/coverage/coverage_stats.py
bugbane/modules/stats/coverage/factory.py
bugbane/modules/stats/coverage/go.py
bugbane/modules/stats/coverage/lcov.py
bugbane/modules/stats/coverage/llvm_summary.py
bugbane/modules/stats/fuzz/__init__.py
bugbane/modules/stats/fuzz/aflplusplus.py
bugbane/modules/stats/fuzz/factory.py
bugbane/modules/stats/fuzz/fuzz_stats.py
bugbane/modules/stats/fuzz/gofuzz.py
bugbane/modules/stats/fuzz/libfuzzer.py
bugbane/tests/__init__.py
bugbane/tests/builder/__init__.py
bugbane/tests/builder/test_builder.py
bugbane/tests/fuzz/__init__.py
bugbane/tests/fuzz/test_cmds.py
bugbane/tests/fuzz/test_stop_conditions.py
bugbane/tests/modules/__init__.py
bugbane/tests/modules/test_coverage_stats.py
bugbane/tests/modules/test_factories.py
bugbane/tests/modules/test_file_utils.py
bugbane/tests/modules/test_format.py
bugbane/tests/modules/test_fuzz_stats.py
bugbane/tests/modules/test_fuzzer_info.py
bugbane/tests/reproduce/__init__.py
bugbane/tests/reproduce/conftest.py
bugbane-0.0.1.dist-info/LICENSE
bugbane-0.0.1.dist-info/METADATA
bugbane-0.0.1.dist-info/WHEEL
bugbane-0.0.1.dist-info/entry_points.txt
bugbane-0.0.1.dist-info/top_level.txt
bugbane-0.0.1.dist-info/RECORD
