Metadata-Version: 2.1
Name: bugbane
Version: 0.0.1
Summary: application security tools for DAST
Home-page: https://github.com/gardatech/bugbane
Author: Valery Korolyov
Author-email: fuzzah@tuta.io
License: Apache-2.0
Platform: UNKNOWN
Classifier: License :: OSI Approved :: Apache Software License
Classifier: Operating System :: OS Independent
Classifier: Programming Language :: Python :: 3
Classifier: Typing :: Typed
Classifier: Framework :: Pytest
Classifier: Framework :: tox
Classifier: Topic :: Security
Classifier: Topic :: Software Development :: Bug Tracking
Classifier: Topic :: Software Development :: Build Tools
Classifier: Topic :: Software Development :: Quality Assurance
Classifier: Topic :: Software Development :: Testing
Classifier: Topic :: Utilities
Requires-Python: >=3.6
License-File: LICENSE
Requires-Dist: beautifulsoup4
Requires-Dist: lxml
Requires-Dist: defectdojo-api
Requires-Dist: typing ; python_version < "3.6"
Requires-Dist: dataclasses ; python_version < "3.7"
Provides-Extra: all
Requires-Dist: requests ; extra == 'all'
Requires-Dist: Jinja2 ; extra == 'all'
Requires-Dist: selenium ; extra == 'all'
Requires-Dist: WeasyPrint (==52.5) ; extra == 'all'
Requires-Dist: pytest ; extra == 'all'
Requires-Dist: pytest-mock ; extra == 'all'
Provides-Extra: dd
Requires-Dist: requests ; extra == 'dd'
Provides-Extra: dev
Requires-Dist: requests ; extra == 'dev'
Requires-Dist: Jinja2 ; extra == 'dev'
Requires-Dist: selenium ; extra == 'dev'
Requires-Dist: WeasyPrint (==52.5) ; extra == 'dev'
Requires-Dist: pytest ; extra == 'dev'
Requires-Dist: pytest-mock ; extra == 'dev'
Requires-Dist: black ; extra == 'dev'
Requires-Dist: build ; extra == 'dev'
Requires-Dist: coverage ; extra == 'dev'
Requires-Dist: pylint ; extra == 'dev'
Requires-Dist: tox ; extra == 'dev'
Requires-Dist: rope ; extra == 'dev'
Requires-Dist: wheel ; extra == 'dev'
Provides-Extra: reporting
Requires-Dist: Jinja2 ; extra == 'reporting'
Requires-Dist: selenium ; extra == 'reporting'
Requires-Dist: WeasyPrint (==52.5) ; extra == 'reporting'
Provides-Extra: test
Requires-Dist: pytest ; extra == 'test'
Requires-Dist: pytest-mock ; extra == 'test'
